roigenerator/__init__.py
roigenerator/__main__.py
roigenerator/ont_adaptive.py
roigenerator-0.1.0.dist-info/METADATA
roigenerator-0.1.0.dist-info/WHEEL
roigenerator-0.1.0.dist-info/entry_points.txt
roigenerator-0.1.0.dist-info/licenses/LICENSE
roigenerator-0.1.0.dist-info/RECORD
