Metadata-Version: 2.4
Name: roigenerator
Version: 0.1.0
Summary: 
License-File: LICENSE
Author: Your Name
Author-email: you@example.com
Requires-Python: >=3.11,<4.0
Classifier: Programming Language :: Python :: 3
Classifier: Programming Language :: Python :: 3.11
Classifier: Programming Language :: Python :: 3.12
Classifier: Programming Language :: Python :: 3.13
Classifier: Programming Language :: Python :: 3.14
Requires-Dist: pandas (>=2.3.3,<3.0.0)
Requires-Dist: pyranges (>=0.1.4,<0.2.0)
